pdf_benchmarker/__init__.py
pdf_benchmarker/evaluation/__init__.py
pdf_benchmarker/evaluation/metric_factory.py
pdf_benchmarker/evaluation/metric_interface.py
pdf_benchmarker/evaluation/metrics/__init__.py
pdf_benchmarker/evaluation/metrics/cer.py
pdf_benchmarker/evaluation/metrics/cosine_similarity.py
pdf_benchmarker/evaluation/metrics/entity_and_predicate.py
pdf_benchmarker/evaluation/metrics/rouge.py
pdf_benchmarker/evaluation/metrics/text_utils.py
pdf_benchmarker/evaluation/metrics/wer.py
pdf_benchmarker/javalib/pdfbox-app-3.0.2.jar
pdf_benchmarker/llm_benchmark/f1_benchmark.py
pdf_benchmarker/models/__init__.py
pdf_benchmarker/models/models.py
pdf_benchmarker/scraper/__init__.py
pdf_benchmarker/scraper/scraper_factory.py
pdf_benchmarker/scraper/scraper_interface.py
pdf_benchmarker/scraper/scrapers/__init__.py
pdf_benchmarker/scraper/scrapers/benchmark_results.db
pdf_benchmarker/scraper/scrapers/llama_parse_scraper.py
pdf_benchmarker/scraper/scrapers/pdf_box_scraper.py
pdf_benchmarker/scraper/scrapers/pdf_miner_scraper.py
pdf_benchmarker/scraper/scrapers/pdf_tika_scraper.py
pdf_benchmarker/scraper/scrapers/py_pdf_scraper.py
pdf_benchmarker/scraper/scrapers/pymupdf_scraper.py
pdf_benchmarker/scraper/scrapers/tesseract_scraper.py
pdf_benchmarker/scraper/scrapers/unstructured_scraper.py
pdf_benchmarker/utils/__init__.py
pdf_benchmarker/utils/benchmark_format_options.py
pdf_benchmarker/utils/csv_logger.py
pdf_benchmarker/utils/decorators.py
pdf_benchmarker/utils/utils.py
pdf_benchmarker-0.1.0.dist-info/METADATA
pdf_benchmarker-0.1.0.dist-info/WHEEL
pdf_benchmarker-0.1.0.dist-info/RECORD
