Metadata-Version: 2.1
Name: pdf-benchmarker
Version: 0.1.0
Summary: Benchmark PDF extraction tools for use with RAG applications
Home-page: https://github.com/the-merge/pdf-benchmarker
License: MIT
Author: Joshua Oliphant
Author-email: joshua.oliphant@hey.com
Requires-Python: >=3.10.1,<3.13
Classifier: License :: OSI Approved :: MIT License
Classifier: Programming Language :: Python :: 3
Classifier: Programming Language :: Python :: 3.11
Classifier: Programming Language :: Python :: 3.12
Requires-Dist: altair (>=5.3.0,<6.0.0)
Requires-Dist: docqa-bench (>=0.1.13,<0.2.0)
Requires-Dist: fpdf (>=1.7.2,<2.0.0)
Requires-Dist: jiwer (>=3.0.4,<4.0.0)
Requires-Dist: llama-parse (>=0.4.2,<0.5.0)
Requires-Dist: matplotlib (>=3.8.4,<4.0.0)
Requires-Dist: pandas (>=2.2.2,<3.0.0)
Requires-Dist: pdf2image (>=1.17.0,<2.0.0)
Requires-Dist: pdfminer-six (>=20231228,<20231229)
Requires-Dist: pillow (>=10.3.0,<11.0.0)
Requires-Dist: psutil (>=5.9.8,<6.0.0)
Requires-Dist: pydantic (>=2.8.2,<3.0.0)
Requires-Dist: pymupdf (>=1.24.4,<2.0.0)
Requires-Dist: pypdf (>=4.2.0,<5.0.0)
Requires-Dist: pytesseract (>=0.3.10,<0.4.0)
Requires-Dist: python-dotenv (>=1.0.1,<2.0.0)
Requires-Dist: rouge_score (>=0.1.2,<0.2.0)
Requires-Dist: spacy (>=3.7.4,<4.0.0)
Requires-Dist: tenacity (>=8.3.0,<9.0.0)
Requires-Dist: testcontainers (>=4.5.0,<5.0.0)
Requires-Dist: tika (>=2.6.0,<3.0.0)
Requires-Dist: torch (>=2.2.2,<2.3.0)
Requires-Dist: transformers (>=4.40.1,<5.0.0)
Requires-Dist: trogon (>=0.5.0,<0.6.0)
Requires-Dist: unstructured (>=0.11.8,<0.12.0)
Project-URL: Repository, https://github.com/the-merge/pdf-benchmarker
